ufanet_intercom_api/__init__.py
ufanet_intercom_api/exceptions.py
ufanet_intercom_api/logger.py
ufanet_intercom_api/models.py
ufanet_intercom_api/wrapper.py
ufanet_intercom_api-0.0.10.dist-info/licenses/LICENSE
ufanet_intercom_api-0.0.10.dist-info/METADATA
ufanet_intercom_api-0.0.10.dist-info/WHEEL
ufanet_intercom_api-0.0.10.dist-info/top_level.txt
ufanet_intercom_api-0.0.10.dist-info/RECORD
